{
  "chaos_ranked": [
    {
      "title": "Ars Technica: Our newsroom AI policy",
      "link": "https://arstechnica.com/staff/2026/04/our-newsroom-ai-policy/",
      "summary": "<a href=\"https://news.ycombinator.com/item?id=47872452\">Comments</a>...",
      "published": "2026-04-23T05:14:05+00:00",
      "domain": "arstechnica.com",
      "scores": {
        "chaos": 18.0,
        "anarchy": 12.0,
        "overall": 15.0
      },
      "keywords": {
        "chaos": [],
        "anarchy": []
      }
    },
    {
      "title": "Boston marathon's good Samaritan loses race time but wins plaudits",
      "link": "https://www.thetimes.com/us/news-today/article/boston-marathon-runners-video-viral-mv2glcvff",
      "summary": "<p>Article URL: <a href=\"https://www.thetimes.com/us/news-today/article/boston-marathon-runners-video-viral-mv2glcvff\">https://www.thetimes.com/us/news-today/article/boston-marathon-runners-video-vira...",
      "published": "2026-04-23T07:51:01+00:00",
      "domain": "thetimes.com",
      "scores": {
        "chaos": 3.0,
        "anarchy": 3.0,
        "overall": 3.0
      },
      "keywords": {
        "chaos": [],
        "anarchy": []
      }
    },
    {
      "title": "Rediscovering the Handcart",
      "link": "https://solar.lowtechmagazine.com/2026/04/rediscovering-the-handcart/",
      "summary": "<p>Article URL: <a href=\"https://solar.lowtechmagazine.com/2026/04/rediscovering-the-handcart/\">https://solar.lowtechmagazine.com/2026/04/rediscovering-the-handcart/</a></p>\n<p>Comments URL: <a href=\"...",
      "published": "2026-04-23T07:50:17+00:00",
      "domain": "solar.lowtechmagazine.com",
      "scores": {
        "chaos": 3.0,
        "anarchy": 3.0,
        "overall": 3.0
      },
      "keywords": {
        "chaos": [],
        "anarchy": []
      }
    },
    {
      "title": "The Second Wave of the API-First Economy",
      "link": "https://brandur.org/second-wave-api-first",
      "summary": "<p>Article URL: <a href=\"https://brandur.org/second-wave-api-first\">https://brandur.org/second-wave-api-first</a></p>\n<p>Comments URL: <a href=\"https://news.ycombinator.com/item?id=47873182\">https://n...",
      "published": "2026-04-23T07:48:43+00:00",
      "domain": "brandur.org",
      "scores": {
        "chaos": 3.0,
        "anarchy": 3.0,
        "overall": 3.0
      },
      "keywords": {
        "chaos": [],
        "anarchy": []
      }
    },
    {
      "title": "Left Behind: A BeOS and Be Incorporated Post-Mortem (2024)",
      "link": "https://macfolkloreradio.com/be/",
      "summary": "<p>Article URL: <a href=\"https://macfolkloreradio.com/be/\">https://macfolkloreradio.com/be/</a></p>\n<p>Comments URL: <a href=\"https://news.ycombinator.com/item?id=47873168\">https://news.ycombinator.co...",
      "published": "2026-04-23T07:47:06+00:00",
      "domain": "macfolkloreradio.com",
      "scores": {
        "chaos": 3.0,
        "anarchy": 3.0,
        "overall": 3.0
      },
      "keywords": {
        "chaos": [],
        "anarchy": []
      }
    },
    {
      "title": "Ask HN: Where are all the AI disasters?",
      "link": "https://news.ycombinator.com/item?id=47873166",
      "summary": "<p>Ok we see AI and agents constantly on HN, but never see people coming clean with there AI disasters. Anyone had disasters or things going wrong?</p>\n<hr />\n<p>Comments URL: <a href=\"https://news.yc...",
      "published": "2026-04-23T07:46:30+00:00",
      "domain": "news.ycombinator.com",
      "scores": {
        "chaos": 3.0,
        "anarchy": 3.0,
        "overall": 3.0
      },
      "keywords": {
        "chaos": [],
        "anarchy": []
      }
    },
    {
      "title": "I am building a cloud",
      "link": "https://crawshaw.io/blog/building-a-cloud",
      "summary": "<a href=\"https://news.ycombinator.com/item?id=47872324\">Comments</a>...",
      "published": "2026-04-23T04:44:19+00:00",
      "domain": "crawshaw.io",
      "scores": {
        "chaos": 3.0,
        "anarchy": 3.0,
        "overall": 3.0
      },
      "keywords": {
        "chaos": [],
        "anarchy": []
      }
    },
    {
      "title": "Malicious KICS Docker Images and VS Code Extensions Hit Checkmarx Supply Chain",
      "link": "https://thehackernews.com/2026/04/malicious-kics-docker-images-and-vs.html",
      "summary": "Cybersecurity researchers have warned of malicious images pushed to the official \"checkmarx/kics\" Docker Hub repository.\nIn an alert published today, software supply chain security company Socket reve...",
      "published": "2026-04-22T23:25:00+05:30",
      "domain": "thehackernews.com",
      "scores": {
        "chaos": 3.0,
        "anarchy": 3.0,
        "overall": 3.0
      },
      "keywords": {
        "chaos": [],
        "anarchy": []
      }
    },
    {
      "title": "Self-Propagating Supply Chain Worm Hijacks npm Packages to Steal Developer Tokens",
      "link": "https://thehackernews.com/2026/04/self-propagating-supply-chain-worm.html",
      "summary": "Cybersecurity researchers have flagged a fresh set of packages that have been compromised by bad actors to deliver a self-propagating worm that spreads through stolen developer npm tokens.\nThe supply ...",
      "published": "2026-04-22T23:03:00+05:30",
      "domain": "thehackernews.com",
      "scores": {
        "chaos": 3.0,
        "anarchy": 3.0,
        "overall": 3.0
      },
      "keywords": {
        "chaos": [],
        "anarchy": []
      }
    },
    {
      "title": "Harvester Deploys Linux GoGra Backdoor in South Asia Using Microsoft Graph API",
      "link": "https://thehackernews.com/2026/04/harvester-deploys-linux-gogra-backdoor.html",
      "summary": "The threat actor known as Harvester has been attributed to a new Linux version of its GoGra backdoor deployed as part of attacks likely targeting entities in South Asia.\n\"The malware uses the legitima...",
      "published": "2026-04-22T20:58:00+05:30",
      "domain": "thehackernews.com",
      "scores": {
        "chaos": 3.0,
        "anarchy": 3.0,
        "overall": 3.0
      },
      "keywords": {
        "chaos": [],
        "anarchy": []
      }
    }
  ],
  "anarchy_ranked": [
    {
      "title": "Ars Technica: Our newsroom AI policy",
      "link": "https://arstechnica.com/staff/2026/04/our-newsroom-ai-policy/",
      "summary": "<a href=\"https://news.ycombinator.com/item?id=47872452\">Comments</a>...",
      "published": "2026-04-23T05:14:05+00:00",
      "domain": "arstechnica.com",
      "scores": {
        "chaos": 18.0,
        "anarchy": 12.0,
        "overall": 15.0
      },
      "keywords": {
        "chaos": [],
        "anarchy": []
      }
    },
    {
      "title": "Boston marathon's good Samaritan loses race time but wins plaudits",
      "link": "https://www.thetimes.com/us/news-today/article/boston-marathon-runners-video-viral-mv2glcvff",
      "summary": "<p>Article URL: <a href=\"https://www.thetimes.com/us/news-today/article/boston-marathon-runners-video-viral-mv2glcvff\">https://www.thetimes.com/us/news-today/article/boston-marathon-runners-video-vira...",
      "published": "2026-04-23T07:51:01+00:00",
      "domain": "thetimes.com",
      "scores": {
        "chaos": 3.0,
        "anarchy": 3.0,
        "overall": 3.0
      },
      "keywords": {
        "chaos": [],
        "anarchy": []
      }
    },
    {
      "title": "Rediscovering the Handcart",
      "link": "https://solar.lowtechmagazine.com/2026/04/rediscovering-the-handcart/",
      "summary": "<p>Article URL: <a href=\"https://solar.lowtechmagazine.com/2026/04/rediscovering-the-handcart/\">https://solar.lowtechmagazine.com/2026/04/rediscovering-the-handcart/</a></p>\n<p>Comments URL: <a href=\"...",
      "published": "2026-04-23T07:50:17+00:00",
      "domain": "solar.lowtechmagazine.com",
      "scores": {
        "chaos": 3.0,
        "anarchy": 3.0,
        "overall": 3.0
      },
      "keywords": {
        "chaos": [],
        "anarchy": []
      }
    },
    {
      "title": "The Second Wave of the API-First Economy",
      "link": "https://brandur.org/second-wave-api-first",
      "summary": "<p>Article URL: <a href=\"https://brandur.org/second-wave-api-first\">https://brandur.org/second-wave-api-first</a></p>\n<p>Comments URL: <a href=\"https://news.ycombinator.com/item?id=47873182\">https://n...",
      "published": "2026-04-23T07:48:43+00:00",
      "domain": "brandur.org",
      "scores": {
        "chaos": 3.0,
        "anarchy": 3.0,
        "overall": 3.0
      },
      "keywords": {
        "chaos": [],
        "anarchy": []
      }
    },
    {
      "title": "Left Behind: A BeOS and Be Incorporated Post-Mortem (2024)",
      "link": "https://macfolkloreradio.com/be/",
      "summary": "<p>Article URL: <a href=\"https://macfolkloreradio.com/be/\">https://macfolkloreradio.com/be/</a></p>\n<p>Comments URL: <a href=\"https://news.ycombinator.com/item?id=47873168\">https://news.ycombinator.co...",
      "published": "2026-04-23T07:47:06+00:00",
      "domain": "macfolkloreradio.com",
      "scores": {
        "chaos": 3.0,
        "anarchy": 3.0,
        "overall": 3.0
      },
      "keywords": {
        "chaos": [],
        "anarchy": []
      }
    },
    {
      "title": "Ask HN: Where are all the AI disasters?",
      "link": "https://news.ycombinator.com/item?id=47873166",
      "summary": "<p>Ok we see AI and agents constantly on HN, but never see people coming clean with there AI disasters. Anyone had disasters or things going wrong?</p>\n<hr />\n<p>Comments URL: <a href=\"https://news.yc...",
      "published": "2026-04-23T07:46:30+00:00",
      "domain": "news.ycombinator.com",
      "scores": {
        "chaos": 3.0,
        "anarchy": 3.0,
        "overall": 3.0
      },
      "keywords": {
        "chaos": [],
        "anarchy": []
      }
    },
    {
      "title": "I am building a cloud",
      "link": "https://crawshaw.io/blog/building-a-cloud",
      "summary": "<a href=\"https://news.ycombinator.com/item?id=47872324\">Comments</a>...",
      "published": "2026-04-23T04:44:19+00:00",
      "domain": "crawshaw.io",
      "scores": {
        "chaos": 3.0,
        "anarchy": 3.0,
        "overall": 3.0
      },
      "keywords": {
        "chaos": [],
        "anarchy": []
      }
    },
    {
      "title": "Malicious KICS Docker Images and VS Code Extensions Hit Checkmarx Supply Chain",
      "link": "https://thehackernews.com/2026/04/malicious-kics-docker-images-and-vs.html",
      "summary": "Cybersecurity researchers have warned of malicious images pushed to the official \"checkmarx/kics\" Docker Hub repository.\nIn an alert published today, software supply chain security company Socket reve...",
      "published": "2026-04-22T23:25:00+05:30",
      "domain": "thehackernews.com",
      "scores": {
        "chaos": 3.0,
        "anarchy": 3.0,
        "overall": 3.0
      },
      "keywords": {
        "chaos": [],
        "anarchy": []
      }
    },
    {
      "title": "Self-Propagating Supply Chain Worm Hijacks npm Packages to Steal Developer Tokens",
      "link": "https://thehackernews.com/2026/04/self-propagating-supply-chain-worm.html",
      "summary": "Cybersecurity researchers have flagged a fresh set of packages that have been compromised by bad actors to deliver a self-propagating worm that spreads through stolen developer npm tokens.\nThe supply ...",
      "published": "2026-04-22T23:03:00+05:30",
      "domain": "thehackernews.com",
      "scores": {
        "chaos": 3.0,
        "anarchy": 3.0,
        "overall": 3.0
      },
      "keywords": {
        "chaos": [],
        "anarchy": []
      }
    },
    {
      "title": "Harvester Deploys Linux GoGra Backdoor in South Asia Using Microsoft Graph API",
      "link": "https://thehackernews.com/2026/04/harvester-deploys-linux-gogra-backdoor.html",
      "summary": "The threat actor known as Harvester has been attributed to a new Linux version of its GoGra backdoor deployed as part of attacks likely targeting entities in South Asia.\n\"The malware uses the legitima...",
      "published": "2026-04-22T20:58:00+05:30",
      "domain": "thehackernews.com",
      "scores": {
        "chaos": 3.0,
        "anarchy": 3.0,
        "overall": 3.0
      },
      "keywords": {
        "chaos": [],
        "anarchy": []
      }
    }
  ],
  "overall_ranked": [
    {
      "title": "Ars Technica: Our newsroom AI policy",
      "link": "https://arstechnica.com/staff/2026/04/our-newsroom-ai-policy/",
      "summary": "<a href=\"https://news.ycombinator.com/item?id=47872452\">Comments</a>...",
      "published": "2026-04-23T05:14:05+00:00",
      "domain": "arstechnica.com",
      "scores": {
        "chaos": 18.0,
        "anarchy": 12.0,
        "overall": 15.0
      },
      "keywords": {
        "chaos": [],
        "anarchy": []
      }
    },
    {
      "title": "Boston marathon's good Samaritan loses race time but wins plaudits",
      "link": "https://www.thetimes.com/us/news-today/article/boston-marathon-runners-video-viral-mv2glcvff",
      "summary": "<p>Article URL: <a href=\"https://www.thetimes.com/us/news-today/article/boston-marathon-runners-video-viral-mv2glcvff\">https://www.thetimes.com/us/news-today/article/boston-marathon-runners-video-vira...",
      "published": "2026-04-23T07:51:01+00:00",
      "domain": "thetimes.com",
      "scores": {
        "chaos": 3.0,
        "anarchy": 3.0,
        "overall": 3.0
      },
      "keywords": {
        "chaos": [],
        "anarchy": []
      }
    },
    {
      "title": "Rediscovering the Handcart",
      "link": "https://solar.lowtechmagazine.com/2026/04/rediscovering-the-handcart/",
      "summary": "<p>Article URL: <a href=\"https://solar.lowtechmagazine.com/2026/04/rediscovering-the-handcart/\">https://solar.lowtechmagazine.com/2026/04/rediscovering-the-handcart/</a></p>\n<p>Comments URL: <a href=\"...",
      "published": "2026-04-23T07:50:17+00:00",
      "domain": "solar.lowtechmagazine.com",
      "scores": {
        "chaos": 3.0,
        "anarchy": 3.0,
        "overall": 3.0
      },
      "keywords": {
        "chaos": [],
        "anarchy": []
      }
    },
    {
      "title": "The Second Wave of the API-First Economy",
      "link": "https://brandur.org/second-wave-api-first",
      "summary": "<p>Article URL: <a href=\"https://brandur.org/second-wave-api-first\">https://brandur.org/second-wave-api-first</a></p>\n<p>Comments URL: <a href=\"https://news.ycombinator.com/item?id=47873182\">https://n...",
      "published": "2026-04-23T07:48:43+00:00",
      "domain": "brandur.org",
      "scores": {
        "chaos": 3.0,
        "anarchy": 3.0,
        "overall": 3.0
      },
      "keywords": {
        "chaos": [],
        "anarchy": []
      }
    },
    {
      "title": "Left Behind: A BeOS and Be Incorporated Post-Mortem (2024)",
      "link": "https://macfolkloreradio.com/be/",
      "summary": "<p>Article URL: <a href=\"https://macfolkloreradio.com/be/\">https://macfolkloreradio.com/be/</a></p>\n<p>Comments URL: <a href=\"https://news.ycombinator.com/item?id=47873168\">https://news.ycombinator.co...",
      "published": "2026-04-23T07:47:06+00:00",
      "domain": "macfolkloreradio.com",
      "scores": {
        "chaos": 3.0,
        "anarchy": 3.0,
        "overall": 3.0
      },
      "keywords": {
        "chaos": [],
        "anarchy": []
      }
    },
    {
      "title": "Ask HN: Where are all the AI disasters?",
      "link": "https://news.ycombinator.com/item?id=47873166",
      "summary": "<p>Ok we see AI and agents constantly on HN, but never see people coming clean with there AI disasters. Anyone had disasters or things going wrong?</p>\n<hr />\n<p>Comments URL: <a href=\"https://news.yc...",
      "published": "2026-04-23T07:46:30+00:00",
      "domain": "news.ycombinator.com",
      "scores": {
        "chaos": 3.0,
        "anarchy": 3.0,
        "overall": 3.0
      },
      "keywords": {
        "chaos": [],
        "anarchy": []
      }
    },
    {
      "title": "I am building a cloud",
      "link": "https://crawshaw.io/blog/building-a-cloud",
      "summary": "<a href=\"https://news.ycombinator.com/item?id=47872324\">Comments</a>...",
      "published": "2026-04-23T04:44:19+00:00",
      "domain": "crawshaw.io",
      "scores": {
        "chaos": 3.0,
        "anarchy": 3.0,
        "overall": 3.0
      },
      "keywords": {
        "chaos": [],
        "anarchy": []
      }
    },
    {
      "title": "Malicious KICS Docker Images and VS Code Extensions Hit Checkmarx Supply Chain",
      "link": "https://thehackernews.com/2026/04/malicious-kics-docker-images-and-vs.html",
      "summary": "Cybersecurity researchers have warned of malicious images pushed to the official \"checkmarx/kics\" Docker Hub repository.\nIn an alert published today, software supply chain security company Socket reve...",
      "published": "2026-04-22T23:25:00+05:30",
      "domain": "thehackernews.com",
      "scores": {
        "chaos": 3.0,
        "anarchy": 3.0,
        "overall": 3.0
      },
      "keywords": {
        "chaos": [],
        "anarchy": []
      }
    },
    {
      "title": "Self-Propagating Supply Chain Worm Hijacks npm Packages to Steal Developer Tokens",
      "link": "https://thehackernews.com/2026/04/self-propagating-supply-chain-worm.html",
      "summary": "Cybersecurity researchers have flagged a fresh set of packages that have been compromised by bad actors to deliver a self-propagating worm that spreads through stolen developer npm tokens.\nThe supply ...",
      "published": "2026-04-22T23:03:00+05:30",
      "domain": "thehackernews.com",
      "scores": {
        "chaos": 3.0,
        "anarchy": 3.0,
        "overall": 3.0
      },
      "keywords": {
        "chaos": [],
        "anarchy": []
      }
    },
    {
      "title": "Harvester Deploys Linux GoGra Backdoor in South Asia Using Microsoft Graph API",
      "link": "https://thehackernews.com/2026/04/harvester-deploys-linux-gogra-backdoor.html",
      "summary": "The threat actor known as Harvester has been attributed to a new Linux version of its GoGra backdoor deployed as part of attacks likely targeting entities in South Asia.\n\"The malware uses the legitima...",
      "published": "2026-04-22T20:58:00+05:30",
      "domain": "thehackernews.com",
      "scores": {
        "chaos": 3.0,
        "anarchy": 3.0,
        "overall": 3.0
      },
      "keywords": {
        "chaos": [],
        "anarchy": []
      }
    }
  ],
  "all_articles": [
    {
      "title": "Boston marathon's good Samaritan loses race time but wins plaudits",
      "link": "https://www.thetimes.com/us/news-today/article/boston-marathon-runners-video-viral-mv2glcvff",
      "summary": "<p>Article URL: <a href=\"https://www.thetimes.com/us/news-today/article/boston-marathon-runners-video-viral-mv2glcvff\">https://www.thetimes.com/us/news-today/article/boston-marathon-runners-video-vira...",
      "published": "2026-04-23T07:51:01+00:00",
      "domain": "thetimes.com",
      "scores": {
        "chaos": 3.0,
        "anarchy": 3.0,
        "overall": 3.0
      },
      "keywords": {
        "chaos": [],
        "anarchy": []
      }
    },
    {
      "title": "Rediscovering the Handcart",
      "link": "https://solar.lowtechmagazine.com/2026/04/rediscovering-the-handcart/",
      "summary": "<p>Article URL: <a href=\"https://solar.lowtechmagazine.com/2026/04/rediscovering-the-handcart/\">https://solar.lowtechmagazine.com/2026/04/rediscovering-the-handcart/</a></p>\n<p>Comments URL: <a href=\"...",
      "published": "2026-04-23T07:50:17+00:00",
      "domain": "solar.lowtechmagazine.com",
      "scores": {
        "chaos": 3.0,
        "anarchy": 3.0,
        "overall": 3.0
      },
      "keywords": {
        "chaos": [],
        "anarchy": []
      }
    },
    {
      "title": "The Second Wave of the API-First Economy",
      "link": "https://brandur.org/second-wave-api-first",
      "summary": "<p>Article URL: <a href=\"https://brandur.org/second-wave-api-first\">https://brandur.org/second-wave-api-first</a></p>\n<p>Comments URL: <a href=\"https://news.ycombinator.com/item?id=47873182\">https://n...",
      "published": "2026-04-23T07:48:43+00:00",
      "domain": "brandur.org",
      "scores": {
        "chaos": 3.0,
        "anarchy": 3.0,
        "overall": 3.0
      },
      "keywords": {
        "chaos": [],
        "anarchy": []
      }
    },
    {
      "title": "Left Behind: A BeOS and Be Incorporated Post-Mortem (2024)",
      "link": "https://macfolkloreradio.com/be/",
      "summary": "<p>Article URL: <a href=\"https://macfolkloreradio.com/be/\">https://macfolkloreradio.com/be/</a></p>\n<p>Comments URL: <a href=\"https://news.ycombinator.com/item?id=47873168\">https://news.ycombinator.co...",
      "published": "2026-04-23T07:47:06+00:00",
      "domain": "macfolkloreradio.com",
      "scores": {
        "chaos": 3.0,
        "anarchy": 3.0,
        "overall": 3.0
      },
      "keywords": {
        "chaos": [],
        "anarchy": []
      }
    },
    {
      "title": "Ask HN: Where are all the AI disasters?",
      "link": "https://news.ycombinator.com/item?id=47873166",
      "summary": "<p>Ok we see AI and agents constantly on HN, but never see people coming clean with there AI disasters. Anyone had disasters or things going wrong?</p>\n<hr />\n<p>Comments URL: <a href=\"https://news.yc...",
      "published": "2026-04-23T07:46:30+00:00",
      "domain": "news.ycombinator.com",
      "scores": {
        "chaos": 3.0,
        "anarchy": 3.0,
        "overall": 3.0
      },
      "keywords": {
        "chaos": [],
        "anarchy": []
      }
    },
    {
      "title": "Ars Technica: Our newsroom AI policy",
      "link": "https://arstechnica.com/staff/2026/04/our-newsroom-ai-policy/",
      "summary": "<a href=\"https://news.ycombinator.com/item?id=47872452\">Comments</a>...",
      "published": "2026-04-23T05:14:05+00:00",
      "domain": "arstechnica.com",
      "scores": {
        "chaos": 18.0,
        "anarchy": 12.0,
        "overall": 15.0
      },
      "keywords": {
        "chaos": [],
        "anarchy": []
      }
    },
    {
      "title": "I am building a cloud",
      "link": "https://crawshaw.io/blog/building-a-cloud",
      "summary": "<a href=\"https://news.ycombinator.com/item?id=47872324\">Comments</a>...",
      "published": "2026-04-23T04:44:19+00:00",
      "domain": "crawshaw.io",
      "scores": {
        "chaos": 3.0,
        "anarchy": 3.0,
        "overall": 3.0
      },
      "keywords": {
        "chaos": [],
        "anarchy": []
      }
    },
    {
      "title": "Malicious KICS Docker Images and VS Code Extensions Hit Checkmarx Supply Chain",
      "link": "https://thehackernews.com/2026/04/malicious-kics-docker-images-and-vs.html",
      "summary": "Cybersecurity researchers have warned of malicious images pushed to the official \"checkmarx/kics\" Docker Hub repository.\nIn an alert published today, software supply chain security company Socket reve...",
      "published": "2026-04-22T23:25:00+05:30",
      "domain": "thehackernews.com",
      "scores": {
        "chaos": 3.0,
        "anarchy": 3.0,
        "overall": 3.0
      },
      "keywords": {
        "chaos": [],
        "anarchy": []
      }
    },
    {
      "title": "Self-Propagating Supply Chain Worm Hijacks npm Packages to Steal Developer Tokens",
      "link": "https://thehackernews.com/2026/04/self-propagating-supply-chain-worm.html",
      "summary": "Cybersecurity researchers have flagged a fresh set of packages that have been compromised by bad actors to deliver a self-propagating worm that spreads through stolen developer npm tokens.\nThe supply ...",
      "published": "2026-04-22T23:03:00+05:30",
      "domain": "thehackernews.com",
      "scores": {
        "chaos": 3.0,
        "anarchy": 3.0,
        "overall": 3.0
      },
      "keywords": {
        "chaos": [],
        "anarchy": []
      }
    },
    {
      "title": "Harvester Deploys Linux GoGra Backdoor in South Asia Using Microsoft Graph API",
      "link": "https://thehackernews.com/2026/04/harvester-deploys-linux-gogra-backdoor.html",
      "summary": "The threat actor known as Harvester has been attributed to a new Linux version of its GoGra backdoor deployed as part of attacks likely targeting entities in South Asia.\n\"The malware uses the legitima...",
      "published": "2026-04-22T20:58:00+05:30",
      "domain": "thehackernews.com",
      "scores": {
        "chaos": 3.0,
        "anarchy": 3.0,
        "overall": 3.0
      },
      "keywords": {
        "chaos": [],
        "anarchy": []
      }
    }
  ]
}