{
  "chaos_ranked": [
    {
      "title": "xAI can't deny Grok makes CSAM anymore. So it's suing users",
      "link": "https://arstechnica.com/tech-policy/2026/07/xai-cant-deny-grok-makes-csam-anymore-so-its-suing-users/",
      "summary": "<p>Article URL: <a href=\"https://arstechnica.com/tech-policy/2026/07/xai-cant-deny-grok-makes-csam-anymore-so-its-suing-users/\">https://arstechnica.com/tech-policy/2026/07/xai-cant-deny-grok-makes-csa...",
      "published": "2026-07-17T19:03:16+00:00",
      "domain": "arstechnica.com",
      "scores": {
        "chaos": 18.0,
        "anarchy": 12.0,
        "overall": 15.0
      },
      "keywords": {
        "chaos": [],
        "anarchy": []
      }
    },
    {
      "title": "New NadMesh Botnet Hunts Exposed AI Services for Cloud Keys and Kubernetes Tokens",
      "link": "https://thehackernews.com/2026/07/new-nadmesh-botnet-hunts-exposed-ai.html",
      "summary": "A Go botnet called NadMesh turned up in early July hunting exposed AI services, and the operator's own dashboard claims 3,811 unique AWS keys.\n\nA Shodan harvester keeps the scan queue stocked with Com...",
      "published": "2026-07-17T22:42:23+05:30",
      "domain": "thehackernews.com",
      "scores": {
        "chaos": 3.0,
        "anarchy": 3.0,
        "overall": 3.0
      },
      "keywords": {
        "chaos": [],
        "anarchy": []
      }
    },
    {
      "title": "GoldenEyeDog Subgroup Linked to DigiCert Breach and Code-Signing Certificate Theft",
      "link": "https://thehackernews.com/2026/07/goldeneyedog-subgroup-linked-to.html",
      "summary": "Cybersecurity researchers have attributed the April 2026 DigiCert security incident to a threat activity cluster dubbed CylindricalCanine.\n\nExpel, which shared technical details of the event, describe...",
      "published": "2026-07-17T22:09:16+05:30",
      "domain": "thehackernews.com",
      "scores": {
        "chaos": 3.0,
        "anarchy": 3.0,
        "overall": 3.0
      },
      "keywords": {
        "chaos": [],
        "anarchy": []
      }
    },
    {
      "title": "Fake Coding Tests Deliver OtterCookie-Aligned Malware Hidden in SVG Flag Images",
      "link": "https://thehackernews.com/2026/07/north-korea-linked-hackers-hide.html",
      "summary": "North Korean threat actors linked to the Contagious Interview campaign have been observed employing steganography in SVG image files to conceal malicious payloads as part of a campaign using fake job ...",
      "published": "2026-07-17T19:18:56+05:30",
      "domain": "thehackernews.com",
      "scores": {
        "chaos": 3.0,
        "anarchy": 3.0,
        "overall": 3.0
      },
      "keywords": {
        "chaos": [],
        "anarchy": []
      }
    },
    {
      "title": "Better Call Sol the Workhorse",
      "link": "https://thezvi.wordpress.com/2026/07/13/better-call-sol-the-workhorse/",
      "summary": "<p>Article URL: <a href=\"https://thezvi.wordpress.com/2026/07/13/better-call-sol-the-workhorse/\">https://thezvi.wordpress.com/2026/07/13/better-call-sol-the-workhorse/</a></p>\n<p>Comments URL: <a href...",
      "published": "2026-07-17T19:03:56+00:00",
      "domain": "thezvi.wordpress.com",
      "scores": {
        "chaos": 3.0,
        "anarchy": 3.0,
        "overall": 3.0
      },
      "keywords": {
        "chaos": [],
        "anarchy": []
      }
    },
    {
      "title": "The instant database scratchpad: xata scratch",
      "link": "https://xata.io/blog/the-instant-database-scratchpad-xata-scratch",
      "summary": "<p>Article URL: <a href=\"https://xata.io/blog/the-instant-database-scratchpad-xata-scratch\">https://xata.io/blog/the-instant-database-scratchpad-xata-scratch</a></p>\n<p>Comments URL: <a href=\"https://...",
      "published": "2026-07-17T19:03:42+00:00",
      "domain": "xata.io",
      "scores": {
        "chaos": 3.0,
        "anarchy": 3.0,
        "overall": 3.0
      },
      "keywords": {
        "chaos": [],
        "anarchy": []
      }
    },
    {
      "title": "JustOverlap \u2013 Scheduling with multiple guests and team availability",
      "link": "https://justoverlap.com/",
      "summary": "<p>Article URL: <a href=\"https://justoverlap.com/\">https://justoverlap.com/</a></p>\n<p>Comments URL: <a href=\"https://news.ycombinator.com/item?id=48951057\">https://news.ycombinator.com/item?id=489510...",
      "published": "2026-07-17T19:03:05+00:00",
      "domain": "justoverlap.com",
      "scores": {
        "chaos": 3.0,
        "anarchy": 3.0,
        "overall": 3.0
      },
      "keywords": {
        "chaos": [],
        "anarchy": []
      }
    },
    {
      "title": "The housing theory of everything (2021)",
      "link": "https://worksinprogress.co/issue/the-housing-theory-of-everything/",
      "summary": "<p>Article URL: <a href=\"https://worksinprogress.co/issue/the-housing-theory-of-everything/\">https://worksinprogress.co/issue/the-housing-theory-of-everything/</a></p>\n<p>Comments URL: <a href=\"https:...",
      "published": "2026-07-17T19:00:13+00:00",
      "domain": "worksinprogress.co",
      "scores": {
        "chaos": 3.0,
        "anarchy": 3.0,
        "overall": 3.0
      },
      "keywords": {
        "chaos": [],
        "anarchy": []
      }
    },
    {
      "title": "SpaceX stock drops to a new low and loses $1 trillion in value in a month",
      "link": "https://www.reddit.com/r/technology/comments/1uz6zsr/spacex_stock_drops_to_a_new_low_and_loses_1/",
      "summary": "<table> <tr><td> <a href=\"https://www.reddit.com/r/technology/comments/1uz6zsr/spacex_stock_drops_to_a_new_low_and_loses_1/\"> <img alt=\"SpaceX stock drops to a new low and loses $1 trillion in value i...",
      "published": "2026-07-17T17:53:51+00:00",
      "domain": "reddit.com",
      "scores": {
        "chaos": 3.0,
        "anarchy": 3.0,
        "overall": 3.0
      },
      "keywords": {
        "chaos": [],
        "anarchy": []
      }
    },
    {
      "title": "Flock Said Its Cameras Don't Track People. Then a Reporter Proved Them Wrong On Video",
      "link": "https://www.reddit.com/r/technology/comments/1uz5y37/flock_said_its_cameras_dont_track_people_then_a/",
      "summary": "<table> <tr><td> <a href=\"https://www.reddit.com/r/technology/comments/1uz5y37/flock_said_its_cameras_dont_track_people_then_a/\"> <img alt=\"Flock Said Its Cameras Don't Track People. Then a Reporter P...",
      "published": "2026-07-17T17:16:27+00:00",
      "domain": "reddit.com",
      "scores": {
        "chaos": 3.0,
        "anarchy": 3.0,
        "overall": 3.0
      },
      "keywords": {
        "chaos": [],
        "anarchy": []
      }
    }
  ],
  "anarchy_ranked": [
    {
      "title": "xAI can't deny Grok makes CSAM anymore. So it's suing users",
      "link": "https://arstechnica.com/tech-policy/2026/07/xai-cant-deny-grok-makes-csam-anymore-so-its-suing-users/",
      "summary": "<p>Article URL: <a href=\"https://arstechnica.com/tech-policy/2026/07/xai-cant-deny-grok-makes-csam-anymore-so-its-suing-users/\">https://arstechnica.com/tech-policy/2026/07/xai-cant-deny-grok-makes-csa...",
      "published": "2026-07-17T19:03:16+00:00",
      "domain": "arstechnica.com",
      "scores": {
        "chaos": 18.0,
        "anarchy": 12.0,
        "overall": 15.0
      },
      "keywords": {
        "chaos": [],
        "anarchy": []
      }
    },
    {
      "title": "New NadMesh Botnet Hunts Exposed AI Services for Cloud Keys and Kubernetes Tokens",
      "link": "https://thehackernews.com/2026/07/new-nadmesh-botnet-hunts-exposed-ai.html",
      "summary": "A Go botnet called NadMesh turned up in early July hunting exposed AI services, and the operator's own dashboard claims 3,811 unique AWS keys.\n\nA Shodan harvester keeps the scan queue stocked with Com...",
      "published": "2026-07-17T22:42:23+05:30",
      "domain": "thehackernews.com",
      "scores": {
        "chaos": 3.0,
        "anarchy": 3.0,
        "overall": 3.0
      },
      "keywords": {
        "chaos": [],
        "anarchy": []
      }
    },
    {
      "title": "GoldenEyeDog Subgroup Linked to DigiCert Breach and Code-Signing Certificate Theft",
      "link": "https://thehackernews.com/2026/07/goldeneyedog-subgroup-linked-to.html",
      "summary": "Cybersecurity researchers have attributed the April 2026 DigiCert security incident to a threat activity cluster dubbed CylindricalCanine.\n\nExpel, which shared technical details of the event, describe...",
      "published": "2026-07-17T22:09:16+05:30",
      "domain": "thehackernews.com",
      "scores": {
        "chaos": 3.0,
        "anarchy": 3.0,
        "overall": 3.0
      },
      "keywords": {
        "chaos": [],
        "anarchy": []
      }
    },
    {
      "title": "Fake Coding Tests Deliver OtterCookie-Aligned Malware Hidden in SVG Flag Images",
      "link": "https://thehackernews.com/2026/07/north-korea-linked-hackers-hide.html",
      "summary": "North Korean threat actors linked to the Contagious Interview campaign have been observed employing steganography in SVG image files to conceal malicious payloads as part of a campaign using fake job ...",
      "published": "2026-07-17T19:18:56+05:30",
      "domain": "thehackernews.com",
      "scores": {
        "chaos": 3.0,
        "anarchy": 3.0,
        "overall": 3.0
      },
      "keywords": {
        "chaos": [],
        "anarchy": []
      }
    },
    {
      "title": "Better Call Sol the Workhorse",
      "link": "https://thezvi.wordpress.com/2026/07/13/better-call-sol-the-workhorse/",
      "summary": "<p>Article URL: <a href=\"https://thezvi.wordpress.com/2026/07/13/better-call-sol-the-workhorse/\">https://thezvi.wordpress.com/2026/07/13/better-call-sol-the-workhorse/</a></p>\n<p>Comments URL: <a href...",
      "published": "2026-07-17T19:03:56+00:00",
      "domain": "thezvi.wordpress.com",
      "scores": {
        "chaos": 3.0,
        "anarchy": 3.0,
        "overall": 3.0
      },
      "keywords": {
        "chaos": [],
        "anarchy": []
      }
    },
    {
      "title": "The instant database scratchpad: xata scratch",
      "link": "https://xata.io/blog/the-instant-database-scratchpad-xata-scratch",
      "summary": "<p>Article URL: <a href=\"https://xata.io/blog/the-instant-database-scratchpad-xata-scratch\">https://xata.io/blog/the-instant-database-scratchpad-xata-scratch</a></p>\n<p>Comments URL: <a href=\"https://...",
      "published": "2026-07-17T19:03:42+00:00",
      "domain": "xata.io",
      "scores": {
        "chaos": 3.0,
        "anarchy": 3.0,
        "overall": 3.0
      },
      "keywords": {
        "chaos": [],
        "anarchy": []
      }
    },
    {
      "title": "JustOverlap \u2013 Scheduling with multiple guests and team availability",
      "link": "https://justoverlap.com/",
      "summary": "<p>Article URL: <a href=\"https://justoverlap.com/\">https://justoverlap.com/</a></p>\n<p>Comments URL: <a href=\"https://news.ycombinator.com/item?id=48951057\">https://news.ycombinator.com/item?id=489510...",
      "published": "2026-07-17T19:03:05+00:00",
      "domain": "justoverlap.com",
      "scores": {
        "chaos": 3.0,
        "anarchy": 3.0,
        "overall": 3.0
      },
      "keywords": {
        "chaos": [],
        "anarchy": []
      }
    },
    {
      "title": "The housing theory of everything (2021)",
      "link": "https://worksinprogress.co/issue/the-housing-theory-of-everything/",
      "summary": "<p>Article URL: <a href=\"https://worksinprogress.co/issue/the-housing-theory-of-everything/\">https://worksinprogress.co/issue/the-housing-theory-of-everything/</a></p>\n<p>Comments URL: <a href=\"https:...",
      "published": "2026-07-17T19:00:13+00:00",
      "domain": "worksinprogress.co",
      "scores": {
        "chaos": 3.0,
        "anarchy": 3.0,
        "overall": 3.0
      },
      "keywords": {
        "chaos": [],
        "anarchy": []
      }
    },
    {
      "title": "SpaceX stock drops to a new low and loses $1 trillion in value in a month",
      "link": "https://www.reddit.com/r/technology/comments/1uz6zsr/spacex_stock_drops_to_a_new_low_and_loses_1/",
      "summary": "<table> <tr><td> <a href=\"https://www.reddit.com/r/technology/comments/1uz6zsr/spacex_stock_drops_to_a_new_low_and_loses_1/\"> <img alt=\"SpaceX stock drops to a new low and loses $1 trillion in value i...",
      "published": "2026-07-17T17:53:51+00:00",
      "domain": "reddit.com",
      "scores": {
        "chaos": 3.0,
        "anarchy": 3.0,
        "overall": 3.0
      },
      "keywords": {
        "chaos": [],
        "anarchy": []
      }
    },
    {
      "title": "Flock Said Its Cameras Don't Track People. Then a Reporter Proved Them Wrong On Video",
      "link": "https://www.reddit.com/r/technology/comments/1uz5y37/flock_said_its_cameras_dont_track_people_then_a/",
      "summary": "<table> <tr><td> <a href=\"https://www.reddit.com/r/technology/comments/1uz5y37/flock_said_its_cameras_dont_track_people_then_a/\"> <img alt=\"Flock Said Its Cameras Don't Track People. Then a Reporter P...",
      "published": "2026-07-17T17:16:27+00:00",
      "domain": "reddit.com",
      "scores": {
        "chaos": 3.0,
        "anarchy": 3.0,
        "overall": 3.0
      },
      "keywords": {
        "chaos": [],
        "anarchy": []
      }
    }
  ],
  "overall_ranked": [
    {
      "title": "xAI can't deny Grok makes CSAM anymore. So it's suing users",
      "link": "https://arstechnica.com/tech-policy/2026/07/xai-cant-deny-grok-makes-csam-anymore-so-its-suing-users/",
      "summary": "<p>Article URL: <a href=\"https://arstechnica.com/tech-policy/2026/07/xai-cant-deny-grok-makes-csam-anymore-so-its-suing-users/\">https://arstechnica.com/tech-policy/2026/07/xai-cant-deny-grok-makes-csa...",
      "published": "2026-07-17T19:03:16+00:00",
      "domain": "arstechnica.com",
      "scores": {
        "chaos": 18.0,
        "anarchy": 12.0,
        "overall": 15.0
      },
      "keywords": {
        "chaos": [],
        "anarchy": []
      }
    },
    {
      "title": "New NadMesh Botnet Hunts Exposed AI Services for Cloud Keys and Kubernetes Tokens",
      "link": "https://thehackernews.com/2026/07/new-nadmesh-botnet-hunts-exposed-ai.html",
      "summary": "A Go botnet called NadMesh turned up in early July hunting exposed AI services, and the operator's own dashboard claims 3,811 unique AWS keys.\n\nA Shodan harvester keeps the scan queue stocked with Com...",
      "published": "2026-07-17T22:42:23+05:30",
      "domain": "thehackernews.com",
      "scores": {
        "chaos": 3.0,
        "anarchy": 3.0,
        "overall": 3.0
      },
      "keywords": {
        "chaos": [],
        "anarchy": []
      }
    },
    {
      "title": "GoldenEyeDog Subgroup Linked to DigiCert Breach and Code-Signing Certificate Theft",
      "link": "https://thehackernews.com/2026/07/goldeneyedog-subgroup-linked-to.html",
      "summary": "Cybersecurity researchers have attributed the April 2026 DigiCert security incident to a threat activity cluster dubbed CylindricalCanine.\n\nExpel, which shared technical details of the event, describe...",
      "published": "2026-07-17T22:09:16+05:30",
      "domain": "thehackernews.com",
      "scores": {
        "chaos": 3.0,
        "anarchy": 3.0,
        "overall": 3.0
      },
      "keywords": {
        "chaos": [],
        "anarchy": []
      }
    },
    {
      "title": "Fake Coding Tests Deliver OtterCookie-Aligned Malware Hidden in SVG Flag Images",
      "link": "https://thehackernews.com/2026/07/north-korea-linked-hackers-hide.html",
      "summary": "North Korean threat actors linked to the Contagious Interview campaign have been observed employing steganography in SVG image files to conceal malicious payloads as part of a campaign using fake job ...",
      "published": "2026-07-17T19:18:56+05:30",
      "domain": "thehackernews.com",
      "scores": {
        "chaos": 3.0,
        "anarchy": 3.0,
        "overall": 3.0
      },
      "keywords": {
        "chaos": [],
        "anarchy": []
      }
    },
    {
      "title": "Better Call Sol the Workhorse",
      "link": "https://thezvi.wordpress.com/2026/07/13/better-call-sol-the-workhorse/",
      "summary": "<p>Article URL: <a href=\"https://thezvi.wordpress.com/2026/07/13/better-call-sol-the-workhorse/\">https://thezvi.wordpress.com/2026/07/13/better-call-sol-the-workhorse/</a></p>\n<p>Comments URL: <a href...",
      "published": "2026-07-17T19:03:56+00:00",
      "domain": "thezvi.wordpress.com",
      "scores": {
        "chaos": 3.0,
        "anarchy": 3.0,
        "overall": 3.0
      },
      "keywords": {
        "chaos": [],
        "anarchy": []
      }
    },
    {
      "title": "The instant database scratchpad: xata scratch",
      "link": "https://xata.io/blog/the-instant-database-scratchpad-xata-scratch",
      "summary": "<p>Article URL: <a href=\"https://xata.io/blog/the-instant-database-scratchpad-xata-scratch\">https://xata.io/blog/the-instant-database-scratchpad-xata-scratch</a></p>\n<p>Comments URL: <a href=\"https://...",
      "published": "2026-07-17T19:03:42+00:00",
      "domain": "xata.io",
      "scores": {
        "chaos": 3.0,
        "anarchy": 3.0,
        "overall": 3.0
      },
      "keywords": {
        "chaos": [],
        "anarchy": []
      }
    },
    {
      "title": "JustOverlap \u2013 Scheduling with multiple guests and team availability",
      "link": "https://justoverlap.com/",
      "summary": "<p>Article URL: <a href=\"https://justoverlap.com/\">https://justoverlap.com/</a></p>\n<p>Comments URL: <a href=\"https://news.ycombinator.com/item?id=48951057\">https://news.ycombinator.com/item?id=489510...",
      "published": "2026-07-17T19:03:05+00:00",
      "domain": "justoverlap.com",
      "scores": {
        "chaos": 3.0,
        "anarchy": 3.0,
        "overall": 3.0
      },
      "keywords": {
        "chaos": [],
        "anarchy": []
      }
    },
    {
      "title": "The housing theory of everything (2021)",
      "link": "https://worksinprogress.co/issue/the-housing-theory-of-everything/",
      "summary": "<p>Article URL: <a href=\"https://worksinprogress.co/issue/the-housing-theory-of-everything/\">https://worksinprogress.co/issue/the-housing-theory-of-everything/</a></p>\n<p>Comments URL: <a href=\"https:...",
      "published": "2026-07-17T19:00:13+00:00",
      "domain": "worksinprogress.co",
      "scores": {
        "chaos": 3.0,
        "anarchy": 3.0,
        "overall": 3.0
      },
      "keywords": {
        "chaos": [],
        "anarchy": []
      }
    },
    {
      "title": "SpaceX stock drops to a new low and loses $1 trillion in value in a month",
      "link": "https://www.reddit.com/r/technology/comments/1uz6zsr/spacex_stock_drops_to_a_new_low_and_loses_1/",
      "summary": "<table> <tr><td> <a href=\"https://www.reddit.com/r/technology/comments/1uz6zsr/spacex_stock_drops_to_a_new_low_and_loses_1/\"> <img alt=\"SpaceX stock drops to a new low and loses $1 trillion in value i...",
      "published": "2026-07-17T17:53:51+00:00",
      "domain": "reddit.com",
      "scores": {
        "chaos": 3.0,
        "anarchy": 3.0,
        "overall": 3.0
      },
      "keywords": {
        "chaos": [],
        "anarchy": []
      }
    },
    {
      "title": "Flock Said Its Cameras Don't Track People. Then a Reporter Proved Them Wrong On Video",
      "link": "https://www.reddit.com/r/technology/comments/1uz5y37/flock_said_its_cameras_dont_track_people_then_a/",
      "summary": "<table> <tr><td> <a href=\"https://www.reddit.com/r/technology/comments/1uz5y37/flock_said_its_cameras_dont_track_people_then_a/\"> <img alt=\"Flock Said Its Cameras Don't Track People. Then a Reporter P...",
      "published": "2026-07-17T17:16:27+00:00",
      "domain": "reddit.com",
      "scores": {
        "chaos": 3.0,
        "anarchy": 3.0,
        "overall": 3.0
      },
      "keywords": {
        "chaos": [],
        "anarchy": []
      }
    }
  ],
  "all_articles": [
    {
      "title": "New NadMesh Botnet Hunts Exposed AI Services for Cloud Keys and Kubernetes Tokens",
      "link": "https://thehackernews.com/2026/07/new-nadmesh-botnet-hunts-exposed-ai.html",
      "summary": "A Go botnet called NadMesh turned up in early July hunting exposed AI services, and the operator's own dashboard claims 3,811 unique AWS keys.\n\nA Shodan harvester keeps the scan queue stocked with Com...",
      "published": "2026-07-17T22:42:23+05:30",
      "domain": "thehackernews.com",
      "scores": {
        "chaos": 3.0,
        "anarchy": 3.0,
        "overall": 3.0
      },
      "keywords": {
        "chaos": [],
        "anarchy": []
      }
    },
    {
      "title": "GoldenEyeDog Subgroup Linked to DigiCert Breach and Code-Signing Certificate Theft",
      "link": "https://thehackernews.com/2026/07/goldeneyedog-subgroup-linked-to.html",
      "summary": "Cybersecurity researchers have attributed the April 2026 DigiCert security incident to a threat activity cluster dubbed CylindricalCanine.\n\nExpel, which shared technical details of the event, describe...",
      "published": "2026-07-17T22:09:16+05:30",
      "domain": "thehackernews.com",
      "scores": {
        "chaos": 3.0,
        "anarchy": 3.0,
        "overall": 3.0
      },
      "keywords": {
        "chaos": [],
        "anarchy": []
      }
    },
    {
      "title": "Fake Coding Tests Deliver OtterCookie-Aligned Malware Hidden in SVG Flag Images",
      "link": "https://thehackernews.com/2026/07/north-korea-linked-hackers-hide.html",
      "summary": "North Korean threat actors linked to the Contagious Interview campaign have been observed employing steganography in SVG image files to conceal malicious payloads as part of a campaign using fake job ...",
      "published": "2026-07-17T19:18:56+05:30",
      "domain": "thehackernews.com",
      "scores": {
        "chaos": 3.0,
        "anarchy": 3.0,
        "overall": 3.0
      },
      "keywords": {
        "chaos": [],
        "anarchy": []
      }
    },
    {
      "title": "Better Call Sol the Workhorse",
      "link": "https://thezvi.wordpress.com/2026/07/13/better-call-sol-the-workhorse/",
      "summary": "<p>Article URL: <a href=\"https://thezvi.wordpress.com/2026/07/13/better-call-sol-the-workhorse/\">https://thezvi.wordpress.com/2026/07/13/better-call-sol-the-workhorse/</a></p>\n<p>Comments URL: <a href...",
      "published": "2026-07-17T19:03:56+00:00",
      "domain": "thezvi.wordpress.com",
      "scores": {
        "chaos": 3.0,
        "anarchy": 3.0,
        "overall": 3.0
      },
      "keywords": {
        "chaos": [],
        "anarchy": []
      }
    },
    {
      "title": "The instant database scratchpad: xata scratch",
      "link": "https://xata.io/blog/the-instant-database-scratchpad-xata-scratch",
      "summary": "<p>Article URL: <a href=\"https://xata.io/blog/the-instant-database-scratchpad-xata-scratch\">https://xata.io/blog/the-instant-database-scratchpad-xata-scratch</a></p>\n<p>Comments URL: <a href=\"https://...",
      "published": "2026-07-17T19:03:42+00:00",
      "domain": "xata.io",
      "scores": {
        "chaos": 3.0,
        "anarchy": 3.0,
        "overall": 3.0
      },
      "keywords": {
        "chaos": [],
        "anarchy": []
      }
    },
    {
      "title": "xAI can't deny Grok makes CSAM anymore. So it's suing users",
      "link": "https://arstechnica.com/tech-policy/2026/07/xai-cant-deny-grok-makes-csam-anymore-so-its-suing-users/",
      "summary": "<p>Article URL: <a href=\"https://arstechnica.com/tech-policy/2026/07/xai-cant-deny-grok-makes-csam-anymore-so-its-suing-users/\">https://arstechnica.com/tech-policy/2026/07/xai-cant-deny-grok-makes-csa...",
      "published": "2026-07-17T19:03:16+00:00",
      "domain": "arstechnica.com",
      "scores": {
        "chaos": 18.0,
        "anarchy": 12.0,
        "overall": 15.0
      },
      "keywords": {
        "chaos": [],
        "anarchy": []
      }
    },
    {
      "title": "JustOverlap \u2013 Scheduling with multiple guests and team availability",
      "link": "https://justoverlap.com/",
      "summary": "<p>Article URL: <a href=\"https://justoverlap.com/\">https://justoverlap.com/</a></p>\n<p>Comments URL: <a href=\"https://news.ycombinator.com/item?id=48951057\">https://news.ycombinator.com/item?id=489510...",
      "published": "2026-07-17T19:03:05+00:00",
      "domain": "justoverlap.com",
      "scores": {
        "chaos": 3.0,
        "anarchy": 3.0,
        "overall": 3.0
      },
      "keywords": {
        "chaos": [],
        "anarchy": []
      }
    },
    {
      "title": "The housing theory of everything (2021)",
      "link": "https://worksinprogress.co/issue/the-housing-theory-of-everything/",
      "summary": "<p>Article URL: <a href=\"https://worksinprogress.co/issue/the-housing-theory-of-everything/\">https://worksinprogress.co/issue/the-housing-theory-of-everything/</a></p>\n<p>Comments URL: <a href=\"https:...",
      "published": "2026-07-17T19:00:13+00:00",
      "domain": "worksinprogress.co",
      "scores": {
        "chaos": 3.0,
        "anarchy": 3.0,
        "overall": 3.0
      },
      "keywords": {
        "chaos": [],
        "anarchy": []
      }
    },
    {
      "title": "SpaceX stock drops to a new low and loses $1 trillion in value in a month",
      "link": "https://www.reddit.com/r/technology/comments/1uz6zsr/spacex_stock_drops_to_a_new_low_and_loses_1/",
      "summary": "<table> <tr><td> <a href=\"https://www.reddit.com/r/technology/comments/1uz6zsr/spacex_stock_drops_to_a_new_low_and_loses_1/\"> <img alt=\"SpaceX stock drops to a new low and loses $1 trillion in value i...",
      "published": "2026-07-17T17:53:51+00:00",
      "domain": "reddit.com",
      "scores": {
        "chaos": 3.0,
        "anarchy": 3.0,
        "overall": 3.0
      },
      "keywords": {
        "chaos": [],
        "anarchy": []
      }
    },
    {
      "title": "Flock Said Its Cameras Don't Track People. Then a Reporter Proved Them Wrong On Video",
      "link": "https://www.reddit.com/r/technology/comments/1uz5y37/flock_said_its_cameras_dont_track_people_then_a/",
      "summary": "<table> <tr><td> <a href=\"https://www.reddit.com/r/technology/comments/1uz5y37/flock_said_its_cameras_dont_track_people_then_a/\"> <img alt=\"Flock Said Its Cameras Don't Track People. Then a Reporter P...",
      "published": "2026-07-17T17:16:27+00:00",
      "domain": "reddit.com",
      "scores": {
        "chaos": 3.0,
        "anarchy": 3.0,
        "overall": 3.0
      },
      "keywords": {
        "chaos": [],
        "anarchy": []
      }
    }
  ]
}